README.txt
settings-distribute.yaml
setup.py
Agatsuma.egg-info/PKG-INFO
Agatsuma.egg-info/SOURCES.txt
Agatsuma.egg-info/dependency_links.txt
Agatsuma.egg-info/not-zip-safe
Agatsuma.egg-info/requires.txt
Agatsuma.egg-info/top_level.txt
agatsuma/__init__.py
agatsuma/enumerator.py
agatsuma/minicache.py
agatsuma/spell_helpers.py
agatsuma/spellbook.py
agatsuma/version.py
agatsuma/adaptations/__init__.py
agatsuma/adaptations/abclasses.py
agatsuma/adaptations/distribute.py
agatsuma/adaptations/mp.py
agatsuma/adaptations/virtualenv_bootstrap.py
agatsuma/commons/__init__.py
agatsuma/commons/algorithms/__init__.py
agatsuma/commons/containers/__init__.py
agatsuma/commons/types/__init__.py
agatsuma/commons/types/atom.py
agatsuma/commons/types/named_const.py
agatsuma/commons/types/singleton.py
agatsuma/core/__init__.py
agatsuma/core/base_core.py
agatsuma/core/mp_core.py
agatsuma/infrastructure/__init__.py
agatsuma/infrastructure/abstract_settings_provider.py
agatsuma/infrastructure/access_proxy.py
agatsuma/infrastructure/json_settings_provider.py
agatsuma/infrastructure/loggers.py
agatsuma/infrastructure/settings.py
agatsuma/infrastructure/settings_light.py
agatsuma/infrastructure/settings_meta.py
agatsuma/infrastructure/yaml_settings_provider.py
agatsuma/interfaces/__init__.py
agatsuma/interfaces/abstract_core_extension.py
agatsuma/interfaces/abstract_spell.py
agatsuma/interfaces/i_filtering_spell.py
agatsuma/interfaces/i_internal_spell.py
agatsuma/interfaces/i_model_spell.py
agatsuma/interfaces/i_pool_event_spell.py
agatsuma/interfaces/i_settings_backend_spell.py
agatsuma/interfaces/i_setup_spell.py
agatsuma/interfaces/i_storage_spell.py
agatsuma/interfaces/settings_backend.py
agatsuma/spells/__init__.py
agatsuma/spells/common/__init__.py
agatsuma/spells/common/core_filters.py
agatsuma/spells/common/core_settings.py
agatsuma/spells/common/core_spell.py
agatsuma/spells/common/settings_backends/__init__.py
agatsuma/spells/common/settings_backends/memcached_backend.py
agatsuma/spells/common/settings_backends/mongo_backend.py
agatsuma/spells/common/storage_drivers/__init__.py
agatsuma/spells/common/storage_drivers/core_memcached.py
