Metadata-Version: 1.0
Name: Agatsuma
Version: 0.2.176.default.3499b00918ca.tip
Summary: Flexible modular metaframework, mostly intended for web but not only
Home-page: http://agatsuma.ritsuka.org/
Author: Fei Wong Reed
Author-email: feiwreed@gmail.com
License: GPL3
Keywords: agatsuma modularity web framework dynamic imports tornado pylons
Platform: UNKNOWN
